cprdspy/LICENSE
cprdspy/MANIFEST.in
cprdspy/README.md
cprdspy/__init__.py
cprdspy/config.py
cprdspy/setup.py
cprdspy/CPR_3D/shpere.py
cprdspy/CPR_3D/shperical_surface.py
cprdspy/CPR_3D/test.ipynb
cprdspy/CPR_3D/test.py
cprdspy/CPR_3D/test_test.ipynb
cprdspy/CPR_3D/utills.py
cprdspy/CPR_js/CPRSJ.html
cprdspy/CPR_js/CPRSP.js
cprdspy/CPR_js/test.html
cprdspy/CPR_matplotlib/CirclePointRoundSourcePure.py
cprdspy/CPR_matplotlib/Untitled-1.ipynb
cprdspy/CPR_matplotlib/Untitled-2.ipynb
cprdspy/CPR_matplotlib/__init__.py
cprdspy/CPR_matplotlib/test.ipynb
cprdspy/CPR_matplotlib/test_arc.ipynb
cprdspy/CPR_matplotlib/Arcs/__init__.py
cprdspy/CPR_matplotlib/Arcs/arc.py
cprdspy/CPR_matplotlib/Circles/circle.py
cprdspy/CPR_matplotlib/Circles/superellipse.ipynb
cprdspy/CPR_matplotlib/Flowers/__init__.py
cprdspy/CPR_matplotlib/Flowers/flower.py
cprdspy/CPR_matplotlib/Flowers/flower_test.ipynb
cprdspy/CPR_matplotlib/Spirals/spiral.py
cprdspy/CPR_matplotlib/Spirals/spiral_test.ipynb
cprdspy/CPR_plotly/CPRSP.py
cprdspy/CPR_plotly/__init__.py
cprdspy/CPR_plotly/canvas.py
cprdspy/CPR_plotly/Arcs/__init__.py
cprdspy/CPR_plotly/Arcs/arc.py
cprdspy/CPR_plotly/Arcs/arc_config.py
cprdspy/CPR_plotly/Arcs/test.ipynb
cprdspy/CPR_plotly/Circles/__init__.py
cprdspy/CPR_plotly/Circles/circle.py
cprdspy/CPR_plotly/Circles/circle1.py
cprdspy/CPR_plotly/Circles/circle_config.py
cprdspy/CPR_plotly/Circles/circle_test.ipynb
cprdspy/CPR_plotly/Circles/test.ipynb
cprdspy/CPR_plotly/Dots/__init__.py
cprdspy/CPR_plotly/Dots/dot.py
cprdspy/CPR_plotly/Dots/dot_config.py
cprdspy/CPR_plotly/Dots/dot_test.ipynb
cprdspy/CPR_plotly/Flowers/__init__.py
cprdspy/CPR_plotly/Flowers/flower.py
cprdspy/CPR_plotly/Flowers/flower_config.py
cprdspy/CPR_plotly/Flowers/flower_config1.py
cprdspy/CPR_plotly/Flowers/flower_config2.py
cprdspy/CPR_plotly/Flowers/flower_config_.py
cprdspy/CPR_plotly/Flowers/flower_test.ipynb
cprdspy/CPR_plotly/Flowers/test1.ipynb
cprdspy/CPR_plotly/Lines/__init__.py
cprdspy-0.2.2.dist-info/METADATA
cprdspy-0.2.2.dist-info/WHEEL
cprdspy-0.2.2.dist-info/licenses/LICENSE
cprdspy-0.2.2.dist-info/RECORD
