Metadata-Version: 2.4
Name: cprdspy
Version: 0.2.2
Summary: CPR可视化创意包
Project-URL: Homepage, https://github.com/lbylzk8/cprdspy
Project-URL: Documentation, https://github.com/lbylzk8/cprdspy#readme
Project-URL: Repository, https://github.com/lbylzk8/cprdspy.git
Project-URL: Issues, https://github.com/lbylzk8/cprdspy/issues
Author: CPR可视化团队
License: MIT
License-File: LICENSE
Keywords: cpr,dash,medical,plotly,visualization
Classifier: Development Status :: 3 - Alpha
Classifier: Intended Audience :: Healthcare Industry
Classifier: License :: OSI Approved :: MIT License
Classifier: Programming Language :: Python :: 3
Classifier: Programming Language :: Python :: 3.8
Classifier: Programming Language :: Python :: 3.9
Classifier: Programming Language :: Python :: 3.10
Classifier: Programming Language :: Python :: 3.11
Classifier: Topic :: Scientific/Engineering :: Medical Science Apps.
Requires-Python: >=3.8
Requires-Dist: dash-router>=0.2.0
Requires-Dist: dash>=3.0.4
Requires-Dist: ipykernel>=6.29.5
Requires-Dist: matplotlib>=3.10.1
Requires-Dist: nbformat==5.10.4
Requires-Dist: numpy>=2.2.5
Requires-Dist: plotly>=6.0.1
